cli_tools.py
cli_tools-1.0.0.dist-info/DESCRIPTION.rst
cli_tools-1.0.0.dist-info/METADATA
cli_tools-1.0.0.dist-info/RECORD
cli_tools-1.0.0.dist-info/WHEEL
cli_tools-1.0.0.dist-info/metadata.json
cli_tools-1.0.0.dist-info/top_level.txt
