Metadata-Version: 2.0
Name: cli-tools
Version: 1.0.0
Summary: Command Line Interface Tools
Home-page: https://github.com/klmitch/cli_tools
Author: Kevin L. Mitchell
Author-email: klmitch@mit.edu
License: UNKNOWN
Platform: UNKNOWN
Classifier: Development Status :: 5 - Production/Stable
Classifier: Environment :: Console
Classifier: Intended Audience :: Developers
Classifier: License :: OSI Approved :: Apache Software License
Classifier: Operating System :: OS Independent
Classifier: Programming Language :: Python :: 2.7
Classifier: Programming Language :: Python :: 3.3
Classifier: Programming Language :: Python :: 3.4
Classifier: Programming Language :: Python :: 3.5
Classifier: Programming Language :: Python :: 3.6
Classifier: Topic :: Software Development :: User Interfaces
Requires-Dist: setuptools
Requires-Dist: six
